<annotation>
	<folder>train</folder>
	<filename>107.jpeg</filename>
	<path>D:\Source Code\Python\dataset\data\train\107.jpeg</path>
	<source>
		<database>Unknown</database>
	</source>
	<size>
		<width>650</width>
		<height>365</height>
		<depth>3</depth>
	</size>
	<segmented>0</segmented>
	<object>
		<name>motorbike</name>
		<pose>Unspecified</pose>
		<truncated>0</truncated>
		<difficult>0</difficult>
		<bndbox>
			<xmin>401</xmin>
			<ymin>55</ymin>
			<xmax>508</xmax>
			<ymax>346</ymax>
		</bndbox>
	</object>
	<object>
		<name>motorbike</name>
		<pose>Unspecified</pose>
		<truncated>0</truncated>
		<difficult>0</difficult>
		<bndbox>
			<xmin>520</xmin>
			<ymin>41</ymin>
			<xmax>590</xmax>
			<ymax>229</ymax>
		</bndbox>
	</object>
	<object>
		<name>motorbike</name>
		<pose>Unspecified</pose>
		<truncated>0</truncated>
		<difficult>0</difficult>
		<bndbox>
			<xmin>373</xmin>
			<ymin>51</ymin>
			<xmax>424</xmax>
			<ymax>209</ymax>
		</bndbox>
	</object>
	<object>
		<name>motorbike</name>
		<pose>Unspecified</pose>
		<truncated>0</truncated>
		<difficult>0</difficult>
		<bndbox>
			<xmin>479</xmin>
			<ymin>50</ymin>
			<xmax>521</xmax>
			<ymax>141</ymax>
		</bndbox>
	</object>
	<object>
		<name>motorbike</name>
		<pose>Unspecified</pose>
		<truncated>0</truncated>
		<difficult>0</difficult>
		<bndbox>
			<xmin>349</xmin>
			<ymin>55</ymin>
			<xmax>395</xmax>
			<ymax>172</ymax>
		</bndbox>
	</object>
	<object>
		<name>car</name>
		<pose>Unspecified</pose>
		<truncated>0</truncated>
		<difficult>0</difficult>
		<bndbox>
			<xmin>9</xmin>
			<ymin>53</ymin>
			<xmax>256</xmax>
			<ymax>225</ymax>
		</bndbox>
	</object>
	<object>
		<name>car</name>
		<pose>Unspecified</pose>
		<truncated>0</truncated>
		<difficult>0</difficult>
		<bndbox>
			<xmin>214</xmin>
			<ymin>52</ymin>
			<xmax>346</xmax>
			<ymax>177</ymax>
		</bndbox>
	</object>
	<object>
		<name>car</name>
		<pose>Unspecified</pose>
		<truncated>0</truncated>
		<difficult>0</difficult>
		<bndbox>
			<xmin>546</xmin>
			<ymin>17</ymin>
			<xmax>623</xmax>
			<ymax>113</ymax>
		</bndbox>
	</object>
</annotation>
